<annotation>
	<folder>hotdog</folder>
	<filename>129092</filename>
	<source>
		<database>Unknown</database>
	</source>
	<size>
		<width>512</width>
		<height>384</height>
		<depth>3</depth>
	</size>
	<segmented>0</segmented>
	<object>
		<name>hotdog</name>
		<pose>Unspecified</pose>
		<truncated>0</truncated>
		<difficult>0</difficult>
		<bndbox>
			<xmin>207</xmin>
			<ymin>38</ymin>
			<xmax>387</xmax>
			<ymax>125</ymax>
		</bndbox>
	</object>
	<object>
		<name>hotdog</name>
		<pose>Unspecified</pose>
		<truncated>0</truncated>
		<difficult>0</difficult>
		<bndbox>
			<xmin>269</xmin>
			<ymin>185</ymin>
			<xmax>495</xmax>
			<ymax>315</ymax>
		</bndbox>
	</object>
<filetype>jpg</filetype></annotation>