<annotation>
	<folder>sushi</folder>
	<filename>1005352</filename>
	<source>
		<database>Unknown</database>
	</source>
	<size>
		<width>512</width>
		<height>306</height>
		<depth>3</depth>
	</size>
	<segmented>0</segmented>
	<object>
		<name>sushi</name>
		<pose>Unspecified</pose>
		<truncated>0</truncated>
		<difficult>0</difficult>
		<bndbox>
			<xmin>61</xmin>
			<ymin>141</ymin>
			<xmax>157</xmax>
			<ymax>235</ymax>
		</bndbox>
	</object>
	<object>
		<name>sushi</name>
		<pose>Unspecified</pose>
		<truncated>0</truncated>
		<difficult>0</difficult>
		<bndbox>
			<xmin>222</xmin>
			<ymin>113</ymin>
			<xmax>376</xmax>
			<ymax>223</ymax>
		</bndbox>
	</object>
<filetype>jpg</filetype></annotation>